teletools/__init__.py
teletools/utils.py
teletools/cipher/__init__.py
teletools/cipher/_file_cipher.py
teletools/cipher/cipher_cli.py
teletools/database/__init__.py
teletools/database/_abr_numeracao.py
teletools/database/_abr_numeracao_sql_queries.py
teletools/database/_abr_portabilidade.py
teletools/database/_abr_portabilidade_sql_queries.py
teletools/database/_abr_prestadoras.py
teletools/database/_abr_sql_queries.py
teletools/database/_database_config.py
teletools/database/abr_database.py
teletools/database/abr_loader.py
teletools/preprocessing/__init__.py
teletools/preprocessing/_number_format.py
teletools-1.0.0.dist-info/METADATA
teletools-1.0.0.dist-info/WHEEL
teletools-1.0.0.dist-info/entry_points.txt
teletools-1.0.0.dist-info/licenses/LICENSE
teletools-1.0.0.dist-info/RECORD
