Metadata-Version: 2.4
Name: teletools
Version: 1.0.0
Summary: Python Utility Functions Library for Call Details Records ( CDRs ) from Brazilian Telecommunications Carriers
Project-URL: homepage, https://deepwiki.com/InovaFiscaliza/teletools
Project-URL: documentation, https://github.com/InovaFiscaliza/teletools/blob/main/README.md
Project-URL: repository, https://github.com/InovaFiscaliza/teletools
Author-email: Maxwel de Souza Freitas <maxwel@maxwelfreitas.com.br>
License-File: LICENSE
Requires-Python: >=3.13
Requires-Dist: duckdb>=1.4.0
Requires-Dist: pandas>=2.3.2
Requires-Dist: psycopg2-binary>=2.9.11
Requires-Dist: python-dotenv>=1.2.1
Requires-Dist: python-gnupg>=0.5.5
Requires-Dist: sqlalchemy>=2.0.44
Requires-Dist: tqdm>=4.67.1
Requires-Dist: typer>=0.19.1
